images_framework/__init__.py
images_framework/alignment/__init__.py
images_framework/alignment/landmarks.py
images_framework/categories/__init__.py
images_framework/categories/accessories.py
images_framework/categories/animals.py
images_framework/categories/appliance.py
images_framework/categories/buildings.py
images_framework/categories/cars.py
images_framework/categories/characters.py
images_framework/categories/electronic.py
images_framework/categories/food.py
images_framework/categories/furniture.py
images_framework/categories/indoor.py
images_framework/categories/kitchen.py
images_framework/categories/outdoor.py
images_framework/categories/panels.py
images_framework/categories/sports.py
images_framework/categories/vehicles.py
images_framework/detection/__init__.py
images_framework/generation/__init__.py
images_framework/recognition/__init__.py
images_framework/segmentation/__init__.py
images_framework/src/__init__.py
images_framework/src/alignment.py
images_framework/src/annotations.py
images_framework/src/categories.py
images_framework/src/component.py
images_framework/src/composite.py
images_framework/src/constants.py
images_framework/src/datasets.py
images_framework/src/detection.py
images_framework/src/generation.py
images_framework/src/recognition.py
images_framework/src/segmentation.py
images_framework/src/utils.py
images_framework/src/viewer.py
images_framework-2025.10.24.dist-info/licenses/LICENSE
images_framework-2025.10.24.dist-info/METADATA
images_framework-2025.10.24.dist-info/WHEEL
images_framework-2025.10.24.dist-info/top_level.txt
images_framework-2025.10.24.dist-info/RECORD
